{"trial_id": "0247", "hyperparameters": {"space": [{"class_name": "Choice", "config": {"name": "activation", "default": "relu", "conditions": [], "values": ["relu", "tanh", "sigmoid", "leaky_relu", "elu", "selu"], "ordered": false}}, {"class_name": "Int", "config": {"name": "first_units", "default": null, "conditions": [], "min_value": 1, "max_value": 100, "step": 2, "sampling": "linear"}}, {"class_name": "Int", "config": {"name": "num_layers", "default": null, "conditions": [], "min_value": 1, "max_value": 10, "step": 1, "sampling": "linear"}}, {"class_name": "Int", "config": {"name": "units_0", "default": null, "conditions": [], "min_value": 1, "max_value": 100, "step": 2, "sampling": "linear"}}, {"class_name": "Choice", "config": {"name": "loss", "default": "binary_crossentropy", "conditions": [], "values": ["binary_crossentropy", "mse"], "ordered": false}}, {"class_name": "Choice", "config": {"name": "optimizer", "default": "adam", "conditions": [], "values": ["adam", "rmsprop", "sgd", "adagrad", "adadelta", "adamax", "nadam"], "ordered": false}}, {"class_name": "Int", "config": {"name": "units_1", "default": null, "conditions": [], "min_value": 1, "max_value": 100, "step": 2, "sampling": "linear"}}, {"class_name": "Int", "config": {"name": "units_2", "default": null, "conditions": [], "min_value": 1, "max_value": 100, "step": 2, "sampling": "linear"}}, {"class_name": "Int", "config": {"name": "units_3", "default": null, "conditions": [], "min_value": 1, "max_value": 100, "step": 2, "sampling": "linear"}}, {"class_name": "Int", "config": {"name": "units_4", "default": null, "conditions": [], "min_value": 1, "max_value": 100, "step": 2, "sampling": "linear"}}, {"class_name": "Int", "config": {"name": "units_5", "default": null, "conditions": [], "min_value": 1, "max_value": 100, "step": 2, "sampling": "linear"}}, {"class_name": "Int", "config": {"name": "units_6", "default": null, "conditions": [], "min_value": 1, "max_value": 100, "step": 2, "sampling": "linear"}}, {"class_name": "Int", "config": {"name": "units_7", "default": null, "conditions": [], "min_value": 1, "max_value": 100, "step": 2, "sampling": "linear"}}, {"class_name": "Int", "config": {"name": "units_8", "default": null, "conditions": [], "min_value": 1, "max_value": 100, "step": 2, "sampling": "linear"}}, {"class_name": "Int", "config": {"name": "units_9", "default": null, "conditions": [], "min_value": 1, "max_value": 100, "step": 2, "sampling": "linear"}}], "values": {"activation": "sigmoid", "first_units": 15, "num_layers": 9, "units_0": 23, "loss": "binary_crossentropy", "optimizer": "sgd", "units_1": 39, "units_2": 91, "units_3": 37, "units_4": 5, "units_5": 15, "units_6": 13, "units_7": 25, "units_8": 89, "units_9": 25, "tuner/epochs": 3, "tuner/initial_epoch": 0, "tuner/bracket": 2, "tuner/round": 0}}, "metrics": {"metrics": {"loss": {"direction": "min", "observations": [{"value": [0.802524209022522], "step": 0}]}, "accuracy": {"direction": "max", "observations": [{"value": [0.45348837971687317], "step": 0}]}, "val_loss": {"direction": "min", "observations": [{"value": [0.8533629775047302], "step": 0}]}, "val_accuracy": {"direction": "max", "observations": [{"value": [0.2931034564971924], "step": 0}]}}}, "score": 0.2931034564971924, "best_step": 0, "status": "COMPLETED", "message": null}